{
"type": "FeatureCollection",
"name": "Coastal_Caution_Area_point",
"crs": { "type": "name", "properties": { "name": "urn:ogc:def:crs:OGC:1.3:CRS84" } },
"features": [
{ "type": "Feature", "properties": { "OBJL": 27, "INFORM": "Shoal to bare reported in 1996", "SCAMIN": 1499999, "SORDAT": "1996", "SORIND": "US,US,graph,Chart 11400", "DSNM": "US3GC06M.000" }, "geometry": { "type": "Point", "coordinates": [ -82.8223769, 28.2293788 ] } }
]
}
