{
"type": "FeatureCollection",
"name": "Harbour_Coastguard_Station_point",
"crs": { "type": "name", "properties": { "name": "urn:ogc:def:crs:OGC:1.3:CRS84" } },
"features": [
{ "type": "Feature", "properties": { "OBJL": 29, "OBJNAM": null, "INFORM": null, "SCAMIN": 29999, "SORDAT": "201305", "SORIND": "US,US,graph,Chart 11425", "DSNM": "US5FL3ZC.000" }, "geometry": { "type": "Point", "coordinates": [ -82.688431799999989, 27.468689 ] } },
{ "type": "Feature", "properties": { "OBJL": 29, "OBJNAM": null, "INFORM": null, "SCAMIN": 17999, "SORDAT": "200810", "SORIND": "US,US,graph,Chart 11416", "DSNM": "US5TPAFG.000" }, "geometry": { "type": "Point", "coordinates": [ -82.630088100000023, 27.756834500000025 ] } },
{ "type": "Feature", "properties": { "OBJL": 29, "OBJNAM": null, "INFORM": null, "SCAMIN": 17999, "SORDAT": "200810", "SORIND": "US,US,graph,Chart 11415", "DSNM": "US5TPAHI.000" }, "geometry": { "type": "Point", "coordinates": [ -82.4533111, 27.92975 ] } },
{ "type": "Feature", "properties": { "OBJL": 29, "OBJNAM": null, "INFORM": null, "SCAMIN": 17999, "SORDAT": "200810", "SORIND": "US,US,graph,Chart 11416", "DSNM": "US5TPAFG.000" }, "geometry": { "type": "Point", "coordinates": [ -82.6249009, 27.7604852 ] } },
{ "type": "Feature", "properties": { "OBJL": 29, "OBJNAM": null, "INFORM": null, "SCAMIN": 21999, "SORDAT": "200607", "SORIND": "US,US,graph,Chart 11411", "DSNM": "US5TPAHD.000" }, "geometry": { "type": "Point", "coordinates": [ -82.832826899999986, 27.948236 ] } }
]
}
